FishShrimpCrab/FishShrimpCrab.py
FishShrimpCrab/__init__.py
project/__init__.py
project/fishhacrap.py
FishShrimpCrab-0.1.1.dist-info/LICENSE
FishShrimpCrab-0.1.1.dist-info/METADATA
FishShrimpCrab-0.1.1.dist-info/WHEEL
FishShrimpCrab-0.1.1.dist-info/top_level.txt
FishShrimpCrab-0.1.1.dist-info/RECORD
