Metadata-Version: 2.1
Name: FishShrimpCrab
Version: 0.1.1
Summary: A traditional HK game
Home-page: https://github.com/LiChinNgai/fishshrimpcrab
Author: Li
Author-email: your.email@example.com
License: UNKNOWN
Platform: UNKNOWN
Classifier: Programming Language :: Python :: 3
Classifier: License :: OSI Approved :: MIT License
Classifier: Operating System :: OS Independent
Requires-Python: >=3.6
